vector_matrix_overloading/__init__.py
vector_matrix_overloading/core.py
vector_matrix_overloading/vector_matrix_overloading.py
vector_matrix_overloading-0.1.0.dist-info/licenses/LICENSE
vector_matrix_overloading-0.1.0.dist-info/METADATA
vector_matrix_overloading-0.1.0.dist-info/WHEEL
vector_matrix_overloading-0.1.0.dist-info/top_level.txt
vector_matrix_overloading-0.1.0.dist-info/RECORD
