Metadata-Version: 2.4
Name: vector-matrix-overloading
Version: 0.1.0
Summary: 벡터와 행렬 연산을 위한 연산자 오버로딩 패키지
Home-page: https://github.com/yourusername/vector-matrix-overloading
Author: Dongbin Shin
Author-email: Dongbin Shin <dongbin369085@gmail.com>
License: MIT
Project-URL: Homepage, https://github.com/yourusername/vector-matrix-overloading
Project-URL: Documentation, https://github.com/yourusername/vector-matrix-overloading
Project-URL: Repository, https://github.com/yourusername/vector-matrix-overloading
Project-URL: Issues, https://github.com/yourusername/vector-matrix-overloading/issues
Keywords: vector,matrix,linear-algebra,operator-overloading,mathematics
Classifier: Development Status :: 3 - Alpha
Classifier: Intended Audience :: Developers
Classifier: Intended Audience :: Education
Classifier: Intended Audience :: Science/Research
Classifier: Topic :: Scientific/Engineering :: Mathematics
Classifier: License :: OSI Approved :: MIT License
Classifier: Programming Language :: Python :: 3
Classifier: Programming Language :: Python :: 3.8
Classifier: Programming Language :: Python :: 3.9
Classifier: Programming Language :: Python :: 3.10
Classifier: Programming Language :: Python :: 3.11
Classifier: Programming Language :: Python :: 3.12
Requires-Python: >=3.8
License-File: LICENSE
Dynamic: author
Dynamic: home-page
Dynamic: license-file
Dynamic: requires-python
